aleixo50/__init__.py
aleixo50/dish.py
aleixo50/dishes.py
aleixo50/rand.py
aleixo50/recipes.json
aleixo50/test_dishes.py
aleixo50/test_rand.py
aleixo50/__pycache__/__init__.cpython-37.pyc
aleixo50/__pycache__/dish.cpython-37.pyc
aleixo50/__pycache__/dishes.cpython-37.pyc
aleixo50/__pycache__/rand.cpython-37.pyc
aleixo50-0.0.4.data/scripts/aleixo50
aleixo50-0.0.4.dist-info/LICENSE
aleixo50-0.0.4.dist-info/METADATA
aleixo50-0.0.4.dist-info/WHEEL
aleixo50-0.0.4.dist-info/top_level.txt
aleixo50-0.0.4.dist-info/RECORD
