Metadata-Version: 2.1
Name: aleixo50
Version: 0.0.4
Summary: Bruno Aleixo's famous 50 Portuguese traditional dishes
Home-page: https://github.com/andrefs/python-aleixo50
Author: André Santos
Author-email: andrefs@andrefs.com
License: UNKNOWN
Platform: UNKNOWN
Classifier: Programming Language :: Python :: 3
Classifier: Operating System :: OS Independent
Classifier: Topic :: Utilities
